wsnet/__init__.py
wsnet/_version.py
wsnet/agent/__init__.py
wsnet/agent/agent.py
wsnet/agent/direct/__init__.py
wsnet/agent/direct/auth.py
wsnet/operator/__init__.py
wsnet/operator/networkproxy.py
wsnet/operator/sspiproxy.py
wsnet/protocol/__init__.py
wsnet/protocol/cmdtypes.py
wsnet/protocol/utils.py
wsnet/protocol/authentication/__init__.py
wsnet/protocol/authentication/autherror.py
wsnet/protocol/authentication/kerberosauth.py
wsnet/protocol/authentication/kerberosauthreply.py
wsnet/protocol/authentication/ntlmauth.py
wsnet/protocol/authentication/ntlmauthreply.py
wsnet/protocol/authentication/ntlmchallenge.py
wsnet/protocol/authentication/ntlmchallengereply.py
wsnet/protocol/authentication/sequenceno.py
wsnet/protocol/authentication/sequencenoreply.py
wsnet/protocol/authentication/sessionkey.py
wsnet/protocol/authentication/sessionkeyreply.py
wsnet/protocol/common/__init__.py
wsnet/protocol/common/err.py
wsnet/protocol/common/info.py
wsnet/protocol/common/inforeply.py
wsnet/protocol/common/listagents.py
wsnet/protocol/common/listagentsreply.py
wsnet/protocol/common/log.py
wsnet/protocol/common/nop.py
wsnet/protocol/common/ok.py
wsnet/protocol/common/stop.py
wsnet/protocol/common/wsncontinue.py
wsnet/protocol/connection/__init__.py
wsnet/protocol/connection/connect.py
wsnet/protocol/connection/resolv.py
wsnet/protocol/connection/serversocketdata.py
wsnet/protocol/connection/socketdata.py
wsnet/protocol/connection/wrapssl.py
wsnet/protocol/fileop/__init__.py
wsnet/protocol/fileop/dircopy.py
wsnet/protocol/fileop/dirls.py
wsnet/protocol/fileop/dirmk.py
wsnet/protocol/fileop/dirmove.py
wsnet/protocol/fileop/dirrm.py
wsnet/protocol/fileop/filecopy.py
wsnet/protocol/fileop/filedata.py
wsnet/protocol/fileop/fileentry.py
wsnet/protocol/fileop/filemove.py
wsnet/protocol/fileop/fileopen.py
wsnet/protocol/fileop/fileread.py
wsnet/protocol/fileop/filerm.py
wsnet/protocol/fileop/filestat.py
wsnet/pyodide/__init__.py
wsnet/pyodide/asyncio_helper.py
wsnet/pyodide/client.py
wsnet-0.1.6.dist-info/METADATA
wsnet-0.1.6.dist-info/WHEEL
wsnet-0.1.6.dist-info/entry_points.txt
wsnet-0.1.6.dist-info/top_level.txt
wsnet-0.1.6.dist-info/RECORD
