Metadata-Version: 2.1
Name: wsnet
Version: 0.1.6
Home-page: https://github.com/skelsec/wsnet
Author: Tamas Jos
Author-email: info@skelsecprojects.com
Classifier: Programming Language :: Python :: 3.7
Classifier: License :: OSI Approved :: MIT License
Classifier: Operating System :: OS Independent
Requires-Python: >=3.7
Requires-Dist: websockets
Requires-Dist: aiohttp
Requires-Dist: aiosmb (>=0.4.4)
Requires-Dist: netifaces (>=0.10.4)
